xpaper/__init__.py
xpaper/linux.py
xpaper/wallpaper.py
xpaper/windows.py
Xpaper-0.2.0.dist-info/LICENSE
Xpaper-0.2.0.dist-info/METADATA
Xpaper-0.2.0.dist-info/WHEEL
Xpaper-0.2.0.dist-info/top_level.txt
Xpaper-0.2.0.dist-info/RECORD
