Metadata-Version: 2.1
Name: Xpaper
Version: 0.2.0
Summary: Cross platform library for managing desktop wallpaper
Home-page: https://github.com/spatocode/Xpaper
Author: Ekene Izukanne
Author-email: ekeneizukanne@gmail.com
License: MIT
Platform: UNKNOWN
Classifier: Programming Language :: Python
Classifier: License :: OSI Approved :: MIT License
Classifier: Operating System :: OS Independent
